mindspore_rl/__init__.py
mindspore_rl/version.py
mindspore_rl/agent/__init__.py
mindspore_rl/agent/actor.py
mindspore_rl/agent/agent.py
mindspore_rl/agent/learner.py
mindspore_rl/agent/trainer.py
mindspore_rl/algorithm/__init__.py
mindspore_rl/algorithm/a2c/__init__.py
mindspore_rl/algorithm/a2c/a2c.py
mindspore_rl/algorithm/a2c/a2c_session.py
mindspore_rl/algorithm/a2c/a2c_trainer.py
mindspore_rl/algorithm/a2c/config.py
mindspore_rl/algorithm/a3c/__init__.py
mindspore_rl/algorithm/a3c/a3c.py
mindspore_rl/algorithm/a3c/a3c_session.py
mindspore_rl/algorithm/a3c/a3c_trainer.py
mindspore_rl/algorithm/a3c/config.py
mindspore_rl/algorithm/a3c_single/__init__.py
mindspore_rl/algorithm/a3c_single/a2c.py
mindspore_rl/algorithm/a3c_single/a2c_session.py
mindspore_rl/algorithm/a3c_single/a3c_single_trainer.py
mindspore_rl/algorithm/a3c_single/config.py
mindspore_rl/algorithm/ac/__init__.py
mindspore_rl/algorithm/ac/ac.py
mindspore_rl/algorithm/ac/ac_session.py
mindspore_rl/algorithm/ac/ac_trainer.py
mindspore_rl/algorithm/ac/config.py
mindspore_rl/algorithm/awac/__init__.py
mindspore_rl/algorithm/awac/awac.py
mindspore_rl/algorithm/awac/awac_session.py
mindspore_rl/algorithm/awac/awac_trainer.py
mindspore_rl/algorithm/awac/config.py
mindspore_rl/algorithm/c51/__init__.py
mindspore_rl/algorithm/c51/c51.py
mindspore_rl/algorithm/c51/c51_session.py
mindspore_rl/algorithm/c51/c51_trainer.py
mindspore_rl/algorithm/c51/c51policy.py
mindspore_rl/algorithm/c51/config.py
mindspore_rl/algorithm/c51/fullyconnectednet_noisy.py
mindspore_rl/algorithm/coma/__init__.py
mindspore_rl/algorithm/coma/coma.py
mindspore_rl/algorithm/coma/coma_session.py
mindspore_rl/algorithm/coma/coma_trainer.py
mindspore_rl/algorithm/coma/config.py
mindspore_rl/algorithm/cql/__init__.py
mindspore_rl/algorithm/cql/config.py
mindspore_rl/algorithm/cql/cql.py
mindspore_rl/algorithm/cql/cql_session.py
mindspore_rl/algorithm/cql/cql_trainer.py
mindspore_rl/algorithm/ddpg/__init__.py
mindspore_rl-0.7.0.dist-info/LICENSE
mindspore_rl-0.7.0.dist-info/METADATA
mindspore_rl-0.7.0.dist-info/WHEEL
mindspore_rl-0.7.0.dist-info/top_level.txt
mindspore_rl-0.7.0.dist-info/RECORD
