Metadata-Version: 2.1
Name: mindspore-rl
Version: 0.7.0
Summary: A MindSpore reinforcement learning framework.
Home-page: https://github.com/mindspore-lab/mindrl
Author: The MindSpore Authors
Author-email: contact@mindspore.cn
License: Apache 2.0
Keywords: mindspore reinforcement learning
Platform: UNKNOWN
Classifier: Development Status :: 4 - Beta
Classifier: Environment :: Console
Classifier: Intended Audience :: Science/Research
Classifier: Intended Audience :: Developers
Classifier: License :: OSI Approved :: Apache Software License
Classifier: Programming Language :: Python :: 3 :: Only
Classifier: Programming Language :: Python :: 3.7
Classifier: Programming Language :: Python :: 3.8
Classifier: Programming Language :: C++
Classifier: Topic :: Scientific/Engineering
Classifier: Topic :: Scientific/Engineering :: Artificial Intelligence
Classifier: Topic :: Software Development
Classifier: Topic :: Software Development :: Libraries
Classifier: Topic :: Software Development :: Libraries :: Python Modules
Requires-Python: >=3.7
Requires-Dist: numpy (>=1.17.0)
Requires-Dist: matplotlib (>=3.1.3)
Requires-Dist: gym (>=0.18.3)
Requires-Dist: pyyaml (==6.0)
Requires-Dist: astor (==0.8.1)
